MANIFEST.in
README.md
pyproject.toml
setup.py
docs/Makefile
docs/conf.py
docs/index.rst
docs/make.bat
src/PyInputPlus.egg-info/PKG-INFO
src/PyInputPlus.egg-info/SOURCES.txt
src/PyInputPlus.egg-info/dependency_links.txt
src/PyInputPlus.egg-info/requires.txt
src/PyInputPlus.egg-info/top_level.txt
src/pyinputplus/__init__.py
tests/test_pyinputplus.py